LICENSE
MANIFEST.in
README.md
setup.py
commonhelper/__init__.py
commonhelper/admin.py
commonhelper/apps.py
commonhelper/mixins.py
commonhelper/models.py
commonhelper/tests.py
commonhelper/utils.py
commonhelper/views.py
commonhelper/migrations/__init__.py
djangocommonhelper.egg-info/PKG-INFO
djangocommonhelper.egg-info/SOURCES.txt
djangocommonhelper.egg-info/dependency_links.txt
djangocommonhelper.egg-info/top_level.txt