Metadata-Version: 2.1
Name: djangocommonhelper
Version: 0.0.1
Summary: Django app that has common features.
Home-page: UNKNOWN
Author: TDS Programming
License: MIT License
Platform: UNKNOWN
Classifier: Framework :: Django
Classifier: License :: OSI Approved :: MIT License
Classifier: Programming Language :: Python :: 3
Classifier: Operating System :: OS Independent
